milestonexprotectwspython/__init__.py
milestonexprotectwspython/xpwalerttype.py
milestonexprotectwspython/xpwalerttypegroup.py
milestonexprotectwspython/xpwapplicationsecurity.py
milestonexprotectwspython/xpwappmessages.py
milestonexprotectwspython/xpwaudiomessage.py
milestonexprotectwspython/xpwauthenticationtype.py
milestonexprotectwspython/xpwbookmarksettings.py
milestonexprotectwspython/xpwcamera.py
milestonexprotectwspython/xpwcameragroup.py
milestonexprotectwspython/xpwcamerasecurity.py
milestonexprotectwspython/xpwcapability.py
milestonexprotectwspython/xpwcollection.py
milestonexprotectwspython/xpwconfiguration.py
milestonexprotectwspython/xpwconst.py
milestonexprotectwspython/xpwdevice.py
milestonexprotectwspython/xpwdevicedisabled.py
milestonexprotectwspython/xpwdevicemapping.py
milestonexprotectwspython/xpwenumcomparable.py
milestonexprotectwspython/xpweventtype.py
milestonexprotectwspython/xpweventtypegroup.py
milestonexprotectwspython/xpwexception.py
milestonexprotectwspython/xpwgroup.py
milestonexprotectwspython/xpwhardware.py
milestonexprotectwspython/xpwhemisphere.py
milestonexprotectwspython/xpwimmervision.py
milestonexprotectwspython/xpwinput.py
milestonexprotectwspython/xpwinputgroup.py
milestonexprotectwspython/xpwinputsecurity.py
milestonexprotectwspython/xpwipix.py
milestonexprotectwspython/xpwjpegdata.py
milestonexprotectwspython/xpwlicense.py
milestonexprotectwspython/xpwlogininfo.py
milestonexprotectwspython/xpwlogintokenexpiredexception.py
milestonexprotectwspython/xpwmanualrecording.py
milestonexprotectwspython/xpwmanualrecordingresult.py
milestonexprotectwspython/xpwmatrixmonitor.py
milestonexprotectwspython/xpwmetadatadevice.py
milestonexprotectwspython/xpwmetadatadevicesecurity.py
milestonexprotectwspython/xpwmetadatatype.py
milestonexprotectwspython/xpwmicrophone.py
milestonexprotectwspython/xpwmicrophonegroup.py
milestonexprotectwspython/xpwmicrophonesecurity.py
milestonexprotectwspython/xpwoutput.py
milestonexprotectwsPython-1.0.2.dist-info/LICENSE
milestonexprotectwsPython-1.0.2.dist-info/METADATA
milestonexprotectwsPython-1.0.2.dist-info/WHEEL
milestonexprotectwsPython-1.0.2.dist-info/top_level.txt
milestonexprotectwsPython-1.0.2.dist-info/RECORD
